container/__init__.py
container/containers.py
container/db.py
container/decorators.py
container/errors.py
containerplus-1.1.0.dist-info/METADATA
containerplus-1.1.0.dist-info/WHEEL
containerplus-1.1.0.dist-info/top_level.txt
containerplus-1.1.0.dist-info/RECORD
